ezmsg/learn/__init__.py
ezmsg/learn/__version__.py
ezmsg/learn/util.py
ezmsg/learn/dim_reduce/__init__.py
ezmsg/learn/dim_reduce/adaptive_decomp.py
ezmsg/learn/dim_reduce/incremental_decomp.py
ezmsg/learn/linear_model/__init__.py
ezmsg/learn/linear_model/adaptive_linear_regressor.py
ezmsg/learn/linear_model/cca.py
ezmsg/learn/linear_model/linear_regressor.py
ezmsg/learn/linear_model/sgd.py
ezmsg/learn/linear_model/slda.py
ezmsg/learn/model/__init__.py
ezmsg/learn/model/cca.py
ezmsg/learn/model/mlp.py
ezmsg/learn/model/mlp_old.py
ezmsg/learn/model/refit_kalman.py
ezmsg/learn/model/rnn.py
ezmsg/learn/model/transformer.py
ezmsg/learn/nlin_model/__init__.py
ezmsg/learn/nlin_model/mlp.py
ezmsg/learn/process/__init__.py
ezmsg/learn/process/adaptive_linear_regressor.py
ezmsg/learn/process/base.py
ezmsg/learn/process/linear_regressor.py
ezmsg/learn/process/mlp_old.py
ezmsg/learn/process/refit_kalman.py
ezmsg/learn/process/rnn.py
ezmsg/learn/process/sgd.py
ezmsg/learn/process/sklearn.py
ezmsg/learn/process/slda.py
ezmsg/learn/process/torch.py
ezmsg/learn/process/transformer.py
ezmsg_learn-1.0.dist-info/METADATA
ezmsg_learn-1.0.dist-info/WHEEL
ezmsg_learn-1.0.dist-info/RECORD
