Metadata-Version: 2.4
Name: ezmsg-learn
Version: 1.0
Summary: ezmsg namespace package for machine learning
Author-email: Chadwick Boulay <chadwick.boulay@gmail.com>
License-Expression: MIT
Requires-Python: >=3.10.15
Requires-Dist: ezmsg-sigproc
Requires-Dist: river>=0.22.0
Requires-Dist: scikit-learn>=1.6.0
Requires-Dist: torch>=2.6.0
